pdfo/fbobyqa.cp312-win_amd64.dll.a
pdfo/fbobyqa.cp312-win_amd64.pyd
pdfo/fbobyqa_classical.cp312-win_amd64.dll.a
pdfo/fbobyqa_classical.cp312-win_amd64.pyd
pdfo/fcobyla.cp312-win_amd64.dll.a
pdfo/fcobyla.cp312-win_amd64.pyd
pdfo/fcobyla_classical.cp312-win_amd64.dll.a
pdfo/fcobyla_classical.cp312-win_amd64.pyd
pdfo/flincoa.cp312-win_amd64.dll.a
pdfo/flincoa.cp312-win_amd64.pyd
pdfo/flincoa_classical.cp312-win_amd64.dll.a
pdfo/flincoa_classical.cp312-win_amd64.pyd
pdfo/fnewuoa.cp312-win_amd64.dll.a
pdfo/fnewuoa.cp312-win_amd64.pyd
pdfo/fnewuoa_classical.cp312-win_amd64.dll.a
pdfo/fnewuoa_classical.cp312-win_amd64.pyd
pdfo/fuobyqa.cp312-win_amd64.dll.a
pdfo/fuobyqa.cp312-win_amd64.pyd
pdfo/fuobyqa_classical.cp312-win_amd64.dll.a
pdfo/fuobyqa_classical.cp312-win_amd64.pyd
pdfo/gethuge.cp312-win_amd64.dll.a
pdfo/gethuge.cp312-win_amd64.pyd
pdfo/_bobyqa.py
pdfo/_cobyla.py
pdfo/_common.py
pdfo/_lincoa.py
pdfo/_newuoa.py
pdfo/_pdfo.py
pdfo/_settings.py
pdfo/_uobyqa.py
pdfo/__init__.py
pdfo/tests/test_pdfo.py
pdfo/tests/__init__.py
pdfo-2.2.0.dist-info/DELVEWHEEL
pdfo-2.2.0.dist-info/LICENCE.txt
pdfo-2.2.0.dist-info/METADATA
pdfo-2.2.0.dist-info/RECORD
pdfo-2.2.0.dist-info/WHEEL
pdfo.libs/libgcc_s_seh-1.dll
pdfo.libs/libquadmath-0.dll
pdfo.libs/libwinpthread-1.dll
