Metadata-Version: 2.1
Name: pdfo
Version: 2.2.0
Summary: Powell's Derivative-Free Optimization solvers
Keywords: blackbox-optimization,constrained-optimization,derivative-free-optimization,hyperparameter-optimization,nonlinear-optimization,numerical-optimization,optimization,optimization-algorithms,optimization-methods,optimization-tools,simulation-based-optimization,unconstrained-optimization,zeroth-order-optimization
Home-page: https://www.pdfo.net
Author-Email: "Tom M. Ragonneau and Zaikun Zhang" <pdfocode@gmail.com>
Maintainer-Email: "Tom M. Ragonneau" <tom.ragonneau@polyu.edu.hk>, Zaikun Zhang <zaikun.zhang@polyu.edu.hk>
License: BSD 3-Clause License
Classifier: Development Status :: 5 - Production/Stable
Classifier: Intended Audience :: Developers
Classifier: Intended Audience :: Education
Classifier: Intended Audience :: Science/Research
Classifier: License :: OSI Approved :: BSD License
Classifier: Operating System :: Unix
Classifier: Operating System :: MacOS
Classifier: Operating System :: POSIX :: Linux
Classifier: Operating System :: Microsoft :: Windows
Classifier: Programming Language :: Fortran
Classifier: Programming Language :: Python :: 3
Classifier: Programming Language :: Python :: 3.8
Classifier: Programming Language :: Python :: 3.9
Classifier: Programming Language :: Python :: 3.10
Classifier: Programming Language :: Python :: 3.11
Classifier: Programming Language :: Python :: 3.12
Classifier: Topic :: Scientific/Engineering
Classifier: Topic :: Scientific/Engineering :: Mathematics
Classifier: Topic :: Software Development :: Libraries
Classifier: Topic :: Software Development :: Libraries :: Python Modules
Project-URL: Homepage, https://www.pdfo.net
Project-URL: Documentation, https://www.pdfo.net
Project-URL: Source, https://github.com/pdfo/pdfo
Project-URL: Download, https://www.pdfo.net/docs.html#releases
Project-URL: Tracker, https://github.com/pdfo/pdfo/issues
Requires-Python: >=3.8
Requires-Dist: numpy>=1.17.0
Requires-Dist: scipy>=1.10.0
Requires-Dist: matplotlib==3.9.0; extra == "doc"
Requires-Dist: numpydoc==1.7.0; extra == "doc"
Requires-Dist: pydata-sphinx-theme==0.15.3; extra == "doc"
Requires-Dist: Sphinx==7.3.7; extra == "doc"
Requires-Dist: sphinxcontrib-googleanalytics==0.4; extra == "doc"
Requires-Dist: sphinx-copybutton==0.5.2; extra == "doc"
Requires-Dist: sphinx-favicon==1.0.1; extra == "doc"
Provides-Extra: doc
